MANIFEST.in
README.md
setup.py
Flask_ServiceLayer.egg-info/PKG-INFO
Flask_ServiceLayer.egg-info/SOURCES.txt
Flask_ServiceLayer.egg-info/dependency_links.txt
Flask_ServiceLayer.egg-info/requires.txt
Flask_ServiceLayer.egg-info/top_level.txt
flask_servicelayer/__init__.py
test_server/__init__.py