Metadata-Version: 1.1
Name: Flask-ServiceLayer
Version: 0.0.4
Summary: Base classes to create a Service Layer in Flask.
Home-page: http://github.com/sysnove/flask-servicelayer
Author: Guillaume Subiron
Author-email: maethor+pip@subiron.org
License: WTFPL
Platform: UNKNOWN
Classifier: Programming Language :: Python
Classifier: Operating System :: OS Independent
Classifier: Intended Audience :: Developers
Classifier: Programming Language :: Python :: 3.3
